setup.py
nisarg_circle/__init__.py
nisarg_circle/circle.py
nisarg_circle.egg-info/PKG-INFO
nisarg_circle.egg-info/SOURCES.txt
nisarg_circle.egg-info/dependency_links.txt
nisarg_circle.egg-info/not-zip-safe
nisarg_circle.egg-info/top_level.txt